[
    {
      "name": "Melody Giles",
      "price": 73,
      "expirience": 15,
      "rating": 2,
      "email": "melodygiles@pigzart.com",
      "phone": "+1 (842) 486-2808",
      "picture": "http://placehold.it/32x32"
    },
    {
      "name": "Kirsten Leonard",
      "price": 76,
      "expirience": 13,
      "rating": 1,
      "email": "kirstenleonard@pigzart.com",
      "phone": "+1 (839) 541-2887",
      "picture": "http://placehold.it/32x32"
    },
    {
      "name": "Foster Tyson",
      "price": 129,
      "expirience": 8,
      "rating": 2,
      "email": "fostertyson@pigzart.com",
      "phone": "+1 (987) 473-2312",
      "picture": "http://placehold.it/32x32"
    },
    {
      "name": "Norris Noble",
      "price": 126,
      "expirience": 12,
      "rating": 0,
      "email": "norrisnoble@pigzart.com",
      "phone": "+1 (843) 422-2174",
      "picture": "http://placehold.it/32x32"
    },
    {
      "name": "Henrietta Bond",
      "price": 71,
      "expirience": 10,
      "rating": 4,
      "email": "henriettabond@pigzart.com",
      "phone": "+1 (850) 578-2465",
      "picture": "http://placehold.it/32x32"
    },
    {
      "name": "Ella Holloway",
      "price": 138,
      "expirience": 9,
      "rating": 1,
      "email": "ellaholloway@pigzart.com",
      "phone": "+1 (987) 431-2165",
      "picture": "http://placehold.it/32x32"
    },
    {
      "name": "Bobbie Baker",
      "price": 84,
      "expirience": 11,
      "rating": 2,
      "email": "bobbiebaker@pigzart.com",
      "phone": "+1 (811) 565-3814",
      "picture": "http://placehold.it/32x32"
    },
    {
      "name": "Shelley Rhodes",
      "price": 130,
      "expirience": 3,
      "rating": 1,
      "email": "shelleyrhodes@pigzart.com",
      "phone": "+1 (818) 588-3841",
      "picture": "http://placehold.it/32x32"
    },
    {
      "name": "Kate Fry",
      "price": 96,
      "expirience": 4,
      "rating": 4,
      "email": "katefry@pigzart.com",
      "phone": "+1 (878) 452-3717",
      "picture": "http://placehold.it/32x32"
    },
    {
      "name": "Jolene Odonnell",
      "price": 127,
      "expirience": 4,
      "rating": 0,
      "email": "joleneodonnell@pigzart.com",
      "phone": "+1 (960) 467-2100",
      "picture": "http://placehold.it/32x32"
    },
    {
      "name": "Maryanne Ford",
      "price": 121,
      "expirience": 12,
      "rating": 0,
      "email": "maryanneford@pigzart.com",
      "phone": "+1 (926) 507-3994",
      "picture": "http://placehold.it/32x32"
    },
    {
      "name": "Barlow Casey",
      "price": 124,
      "expirience": 4,
      "rating": 3,
      "email": "barlowcasey@pigzart.com",
      "phone": "+1 (980) 482-2984",
      "picture": "http://placehold.it/32x32"
    },
    {
      "name": "Bender Whitehead",
      "price": 113,
      "expirience": 10,
      "rating": 5,
      "email": "benderwhitehead@pigzart.com",
      "phone": "+1 (977) 433-2024",
      "picture": "http://placehold.it/32x32"
    },
    {
      "name": "Therese Herring",
      "price": 132,
      "expirience": 6,
      "rating": 1,
      "email": "thereseherring@pigzart.com",
      "phone": "+1 (831) 513-2227",
      "picture": "http://placehold.it/32x32"
    },
    {
      "name": "Winters Larson",
      "price": 141,
      "expirience": 8,
      "rating": 4,
      "email": "winterslarson@pigzart.com",
      "phone": "+1 (926) 551-3833",
      "picture": "http://placehold.it/32x32"
    },
    {
      "name": "Spence Jarvis",
      "price": 143,
      "expirience": 11,
      "rating": 0,
      "email": "spencejarvis@pigzart.com",
      "phone": "+1 (826) 527-3127",
      "picture": "http://placehold.it/32x32"
    },
    {
      "name": "Gaines Estrada",
      "price": 125,
      "expirience": 7,
      "rating": 4,
      "email": "gainesestrada@pigzart.com",
      "phone": "+1 (953) 550-3787",
      "picture": "http://placehold.it/32x32"
    },
    {
      "name": "Eula Clayton",
      "price": 146,
      "expirience": 7,
      "rating": 0,
      "email": "eulaclayton@pigzart.com",
      "phone": "+1 (954) 469-3855",
      "picture": "http://placehold.it/32x32"
    },
    {
      "name": "Katherine Turner",
      "price": 97,
      "expirience": 1,
      "rating": 4,
      "email": "katherineturner@pigzart.com",
      "phone": "+1 (896) 530-2900",
      "picture": "http://placehold.it/32x32"
    },
    {
      "name": "Wagner Gentry",
      "price": 141,
      "expirience": 14,
      "rating": 5,
      "email": "wagnergentry@pigzart.com",
      "phone": "+1 (994) 568-3277",
      "picture": "http://placehold.it/32x32"
    },
    {
      "name": "Barker Duncan",
      "price": 83,
      "expirience": 0,
      "rating": 2,
      "email": "barkerduncan@pigzart.com",
      "phone": "+1 (992) 445-3230",
      "picture": "http://placehold.it/32x32"
    }
  ]